lvm_read_comma.py
lvm_read_comma-1.32.dist-info/LICENSE
lvm_read_comma-1.32.dist-info/METADATA
lvm_read_comma-1.32.dist-info/WHEEL
lvm_read_comma-1.32.dist-info/top_level.txt
lvm_read_comma-1.32.dist-info/RECORD
