Metadata-Version: 2.1
Name: lvm_read_comma
Version: 1.32
Summary: LabView Measurement File Reader
Home-page: https://github.com/Professor-0/lvm_read
Author: Janko Slavič et al.
Author-email: Theo Waltwood <professor-000@outlook.com>
Project-URL: Homepage, https://github.com/professor-000/lvm_read
Project-URL: Issues, https://github.com/professor-000/lvm_read/issues
Classifier: Programming Language :: Python :: 3
Classifier: License :: OSI Approved :: MIT License
Classifier: Operating System :: OS Independent
Requires-Python: >=3.8
License-File: LICENSE
